{"html_attributions": [], "results": [{"formatted_address": "Crockett Independent School District, TX, USA", "geometry": {"location": {"lat": 31.3071007, "lng": -95.4568133}, "viewport": {"northeast": {"lat": 31.429878, "lng": -95.231623}, "southwest": {"lat": 31.176233, "lng": -95.7479701}}}, "icon": "https://maps.gstatic.com/mapfiles/place_api/icons/geocode-71.png", "id": "300b5e4dcd5614936630142cefc0410f280b94c4", "name": "Crockett Independent School District", "place_id": "ChIJzzozVIfER4YRuX1Ifn6ppeY", "reference": "ChIJzzozVIfER4YRuX1Ifn6ppeY", "types": ["political"]}], "status": "OK"}