{"html_attributions": [], "results": [{"formatted_address": "Lytle Independent School District, TX, USA", "geometry": {"location": {"lat": 29.1997185, "lng": -98.770147}, "viewport": {"northeast": {"lat": 29.250673, "lng": -98.688324}, "southwest": {"lat": 29.1302719, "lng": -98.8382261}}}, "icon": "https://maps.gstatic.com/mapfiles/place_api/icons/geocode-71.png", "id": "020c0230109b362a171f9e46afd1cd93b0a3bc92", "name": "Lytle Independent School District", "place_id": "ChIJbcwOeJRLXIYR34bmi4RKoFU", "reference": "ChIJbcwOeJRLXIYR34bmi4RKoFU", "types": ["political"]}], "status": "OK"}