{"html_attributions": [], "results": [{"formatted_address": "1201 Upton St, Rankin, TX 79778, United States", "geometry": {"location": {"lat": 31.23116959999999, "lng": -101.9417193}, "viewport": {"northeast": {"lat": 31.23253047989273, "lng": -101.9404039701073}, "southwest": {"lat": 31.22983082010728, "lng": -101.9431036298927}}}, "icon": "https://maps.gstatic.com/mapfiles/place_api/icons/school-71.png", "id": "897a94f4a725ccdb6c9826d8fed5657c92c47abd", "name": "Rankin Independent School District", "photos": [{"height": 4077, "html_attributions": ["<a href=\"https://maps.google.com/maps/contrib/104564502513165473495\">Sammy Wyatt</a>"], "photo_reference": "CmRaAAAAU2kXDaTNhQbPxRsi7HOdZmxtQ83mWHDGSt929yRCsyrPqdSsg2WMfq-5-QrEzLh7-ahBTzjWa2iX2T99_MFkwFKz4hTbC4MMzIGXxrD4FZRHq1olOXnGNVxM-QpuBrUcEhCGLQQ5z2ydU8sGdPGmdyeeGhSIlnUPE9dyh2TOYNAxEPOYkOIZJQ", "width": 6109}], "place_id": "ChIJP_8kQF36-YYRKjXvSooAzIE", "plus_code": {"compound_code": "63J5+F8 Rankin, Texas", "global_code": "853W63J5+F8"}, "rating": 0, "reference": "ChIJP_8kQF36-YYRKjXvSooAzIE", "types": ["school", "point_of_interest", "establishment"], "user_ratings_total": 0}], "status": "OK"}