{"html_attributions": [], "results": [{"formatted_address": "701 Bowie Ave, Santa Anna, TX 76878, United States", "geometry": {"location": {"lat": 31.7373173, "lng": -99.322763}, "viewport": {"northeast": {"lat": 31.73869852989272, "lng": -99.32141607010728}, "southwest": {"lat": 31.73599887010728, "lng": -99.32411572989272}}}, "icon": "https://maps.gstatic.com/mapfiles/place_api/icons/school-71.png", "id": "7c0957c80d97b4a894c6b5e08d64686ca4cdb1b9", "name": "SANTA ANNA INDEPENDENT SCHOOL DISTRICT", "place_id": "ChIJGWJ_9tU2V4YRSrsNCAvYiGo", "plus_code": {"compound_code": "PMPG+WV Santa Anna, Texas", "global_code": "8632PMPG+WV"}, "rating": 0, "reference": "ChIJGWJ_9tU2V4YRSrsNCAvYiGo", "types": ["school", "point_of_interest", "establishment"], "user_ratings_total": 0}], "status": "OK"}